insiders-4.1.0.dist-info/METADATA
insiders-4.1.0.dist-info/WHEEL
insiders-4.1.0.dist-info/entry_points.txt
insiders-4.1.0.dist-info/licenses/LICENSE
insiders/__init__.py
insiders/__main__.py
insiders/_internal/__init__.py
insiders/_internal/cli.py
insiders/_internal/clients/__init__.py
insiders/_internal/clients/github.py
insiders/_internal/clients/index.py
insiders/_internal/clients/polar.py
insiders/_internal/clients/pypi.py
insiders/_internal/config.py
insiders/_internal/debug.py
insiders/_internal/defaults.py
insiders/_internal/logger.py
insiders/_internal/models.py
insiders/_internal/ops/__init__.py
insiders/_internal/ops/backlog.py
insiders/_internal/ops/projects.py
insiders/_internal/ops/report.py
insiders/_internal/ops/sponsors.py
insiders/py.typed
insiders-4.1.0.dist-info/RECORD
