Metadata-Version: 2.4
Name: insiders
Version: 4.1.0
Summary: Manage your Insiders projects.
Author-Email: =?utf-8?q?Timoth=C3=A9e_Mazzucotelli?= <dev@pawamoy.fr>
License-Expression: ISC
License-File: LICENSE
Classifier: Development Status :: 4 - Beta
Classifier: Intended Audience :: Developers
Classifier: Programming Language :: Python
Classifier: Programming Language :: Python :: 3
Classifier: Programming Language :: Python :: 3 :: Only
Classifier: Programming Language :: Python :: 3.10
Classifier: Programming Language :: Python :: 3.11
Classifier: Programming Language :: Python :: 3.12
Classifier: Programming Language :: Python :: 3.13
Classifier: Programming Language :: Python :: 3.14
Classifier: Topic :: Utilities
Classifier: Typing :: Typed
Project-URL: Homepage, https://pawamoy.github.io/insiders
Project-URL: Documentation, https://pawamoy.github.io/insiders
Project-URL: Changelog, https://pawamoy.github.io/insiders/changelog
Project-URL: Repository, https://github.com/pawamoy/insiders-project
Project-URL: Issues, https://github.com/pawamoy/insiders-project/issues
Project-URL: Discussions, https://github.com/pawamoy/insiders-project/discussions
Project-URL: Gitter, https://gitter.im/insiders/community
Project-URL: Funding, https://github.com/sponsors/pawamoy
Requires-Python: >=3.10
Requires-Dist: build>=1.2
Requires-Dist: cappa>=0.26.3
Requires-Dist: copier>=9.5
Requires-Dist: copier-templates-extensions>=0.3
Requires-Dist: failprint>=1.0
Requires-Dist: httpx>=0.28
Requires-Dist: loguru>=0.7
Requires-Dist: packaging>=24.2
Requires-Dist: platformdirs>=4.3
Requires-Dist: psutil>=7.0
Requires-Dist: pypiserver>=2.3
Requires-Dist: rich>=13.9
Requires-Dist: tomli>=2.2
Requires-Dist: twine>=6.1
Requires-Dist: typing-extensions>=4.0; python_version < "3.11"
Requires-Dist: unearth>=0.17
